Workbook

Sheet Read Me
B2: AI Impact Assessment: screening, DPIA, FRIA and risk workbook
B3: AI Governance Series, Part 5: github.com/NarendraKarki/ai-governance
B5: What this workbook is for
B6: An AI impact assessment asks one question before a system goes live (who could this harm, and what do we do about it?) and records the answer. In the UK and the EU that question is required by law in two forms. This workbook helps you work out which applies to each AI system, and then write it.
B8: The two assessments
B9: Data protection impact assessment (DPIA) | C9: UK GDPR and EU GDPR, Article 35. Required before processing that is likely to result in a high risk to people. Always required where there is (a) systematic and extensive evaluation of people based on automated processing, including profiling, on which decisions with legal or similarly significant effects are based; (b) large-scale processing of special category data such as health data; or (c) large-scale systematic monitoring of a publicly accessible area. It must describe the processing and its purposes, assess necessity and proportionality, assess the risks to people, and set out the measures. Applies now, in both the UK and the EU.
B10: Fundamental rights impact assessment (FRIA) | C10: EU AI Act, Article 27. Required of deployers of Annex III high-risk AI systems (other than critical infrastructure, point 2) that are public bodies or private entities providing public services, and of every deployer of credit-scoring systems (Annex III 5(b)) or life and health insurance risk-assessment and pricing systems (Annex III 5(c)). Contents: the processes the system is used in; the period and frequency of use; the people and groups affected; the specific risks of harm to them; human oversight; and what is done if the risks materialise. The results are notified to the market surveillance authority. It can cross-refer to, or include parts of, an existing DPIA (Article 27(4)). Applies from 2 December 2027 to systems put into service from then, and to earlier systems only if their design changes significantly (Article 111(2)). The UK has no equivalent.
B12: If it is not done
B13: Order to stop | C13: The regulator can impose a temporary or definitive limitation on processing, including a ban (UK GDPR and GDPR Art 58(2)(f)). For a pricing model, that means switching it off.
B14: Fine for the missing DPIA | C14: UK: up to £8,700,000 or 2% of total worldwide annual turnover, whichever is higher, for breach of Article 35 alone (UK GDPR Art 83(4)(a)). No harm to a customer has to have occurred.
B15: Missing FRIA | C15: The AI Act sets no fine of its own for Article 27: its fine list for operators (Art 99(4)) covers deployer duties under Article 26 but not Article 27. Penalties are left to each Member State (Art 99(1)).
B16: Automated decisions on health data | C16: UK: a significant decision based entirely or partly on special category data such as health data may not be taken solely by automated means unless the decision rests entirely on data given with explicit consent, or is necessary for a contract or required or authorised by law and the substantial public interest condition applies (UK GDPR Art 22B). Where a significant decision is solely automated, the person must be able to get information, make representations, obtain human intervention and contest it (Art 22C).
B18: Impact assessment or risk register?
B19: Impact assessment | C19: One system, written before it goes live and reopened when it changes. It asks what the system could do to people, so every risk here is rated on severity to people. A breach or an attack appears through the harm it does to them.
B20: AI risk register | C20: Every AI system, kept permanently. Each risk is rated twice: severity to people and severity to the organisation: fines, downtime, claims, reputation, the cost of being hacked. Technical vulnerabilities sit in the security register and are cross-referenced. The Part 4 workbook is a worked register.
B21: How they connect | C21: The assessment finds risks to people and hands them to the register (column P). The register tracks them to closure and adds the organisation's own risks. A register trigger (a retrain, a new data source, an incident) reopens the assessment.
B23: How to use it
B24: 1. Screening | C24: One row per AI system. Answer the questions; the workbook shows which assessment is required. Where one is not required, write the reason; that record is part of the control.
B25: 2. DPIA | C25: Write it for every system the screen marks as required, before the processing starts.
B26: 3. FRIA | C26: Write it for every EU-deployed system the screen marks as required, before first use. Point to the DPIA wherever it already covers an element.
B27: 4. Risks | C27: One row per risk to people, rated before and after the measures. Both assessments draw on the same rows. Column P links each row to the AI risk register.
B28: 5. Summary | C28: Live counts from the worked example sheets.
B30: Scales (same as Part 4)
B31: Severity to people (1-4) | C31: 1 inconvenience, reversible on request. 2 financial loss or distress, recoverable. 3 significant loss of access, opportunity or money, hard to reverse. 4 serious or lasting harm, or harm to many people.
B32: Likelihood (1-4) | C32: 1 not expected in the system's life. 2 could happen. 3 expected to happen at some point. 4 expected to happen regularly.
B33: Score and band | C33: Score = severity x likelihood (1-16). Band: 12-16 Critical, 8-9 High, 4-6 Medium, 1-3 Low. Calculated for the risk before and after the measures.
B35: Colour key
B36: Yellow cells | C36: Cells to fill in on the template sheets.
B37: Critical | C37: Risk band
B38: High | C38: Risk band
B39: Medium | C39: Risk band
B40: Low | C40: Risk band
B42: The worked example
B43: Northgate Life & Health (synthetic): a UK-headquartered insurer with a subsidiary in Ireland serving EU customers. Its underwriting model UW-1 reads the application, declared medical history, a GP report obtained with the applicant's consent and, for customers who join the wellness programme, the step count from a wearable, and returns accept, decline or a premium loading. The model's design notes classed the step count as lifestyle data. The assessment applied the test in Article 4(15): personal data that reveals information about a person's health status is data concerning health. A step count used to judge health risk does exactly that, so it was reclassified as health data.
B45: Sources
B46: EU AI Act | C46: Regulation (EU) 2024/1689 as consolidated on 27 July 2026 (CELEX 02024R1689-20260727): Articles 27, 99, 111 and 113, Annex III point 5. Read in the held text.
B47: EU GDPR | C47: Regulation (EU) 2016/679, Articles 4(15) and 35, EUR-Lex consolidated text.
B48: UK GDPR | C48: Articles 4(15), 22B, 22C, 35, 58(2)(f) and 83(4): revised text held (up to date to 21 August 2026) and legislation.gov.uk, September 2026.
B50: Educational material, not legal advice. The insurer, its systems and its people are fictional. Have your DPO or legal counsel review any assessment before it is relied on.

Sheet Summary
B2: Summary: worked example
B3: Live counts from the Screening and Risks sheets.
B5: Screening
B6: Result | C6: DPIA | D6: FRIA
B7: Required | C7: =COUNTIF(Screening!$K$4:$K$100,"Required*") -> 2 | D7: =COUNTIF(Screening!$L$4:$L$100,"Required*") -> 1
B8: Not required: reason recorded | C8: =COUNTIF(Screening!$K$4:$K$100,"Not required*") -> 2 | D8: =COUNTIF(Screening!$L$4:$L$100,"Not required*") -> 3
B9: AI systems screened | C9: =COUNTA(Screening!$A$4:$A$100) -> 4
B11: Risks to people, before and after the measures
B12: Band | C12: Before | D12: After
B13: Critical | C13: =COUNTIF(Risks!$G$4:$G$100,B13) -> 2 | D13: =COUNTIF(Risks!$M$4:$M$100,B13) -> 0
B14: High | C14: =COUNTIF(Risks!$G$4:$G$100,B14) -> 2 | D14: =COUNTIF(Risks!$M$4:$M$100,B14) -> 0
B15: Medium | C15: =COUNTIF(Risks!$G$4:$G$100,B15) -> 5 | D15: =COUNTIF(Risks!$M$4:$M$100,B15) -> 1
B16: Low | C16: =COUNTIF(Risks!$G$4:$G$100,B16) -> 0 | D16: =COUNTIF(Risks!$M$4:$M$100,B16) -> 8
B17: Total risks | C17: =SUM(C13:C16) -> 9 | D17: =SUM(D13:D16) -> 9
B19: Risks still open or mitigating | C19: =COUNTIF(Risks!$N$4:$N$100,"open")+COUNTIF(Risks!$N$4:$N$100,"mitigating") -> 5

Sheet Screening
A1: Screening
A2: One row per AI system. Answer C-J; K and L are calculated. Where an assessment is not required, record the reason in M.
A3: ID | B3: AI system | C3: Processes personal data? | D3: Automated evaluation or profiling with legal or similarly significant effects? (Art 35(3)(a)) | E3: Special category data (e.g. health) at large scale? (Art 35(3)(b)) | F3: Systematic monitoring of a public area at large scale? (Art 35(3)(c)) | G3: Otherwise likely to be high risk to people? (Art 35(1)) | H3: Used in the EU? | I3: High-risk under Annex III (other than point 2)? | J3: Deployer type (Art 27(1)) | K3: DPIA | L3: FRIA | M3: Reason recorded / notes | N3: Decision owner
A4: S1 | B4: UW-1 underwriting model | C4: Yes | D4: Yes | E4: Yes | F4: No | G4: Yes | H4: Yes | I4: Yes | J4: Life or health insurance (Annex III 5(c)) | K4: =IF(C4="","",IF(C4="No","Not required: no personal data",IF(OR(D4="Yes",E4="Yes",F4="Yes",G4="Yes"),"Required: before processing","Not required: record the reason"))) -> Required: before processing | L4: =IF(H4="","",IF(AND(H4="Yes",I4="Yes",J4<>"",J4<>"None of these"),"Required: before first use, from 2 Dec 2027","Not required: record the reason")) -> Required: before first use, from 2 Dec 2027 | M4: Accept, decline and premium loading for individual health and life cover. Both DPIA triggers met. Annex III 5(c) system deployed in the EU by the Irish subsidiary. | N4: Chief Underwriting Officer
A5: S2 | B5: Claims fraud screening | C5: Yes | D5: Yes | E5: Yes | F5: No | G5: Yes | H5: Yes | I5: No | J5: None of these | K5: =IF(C5="","",IF(C5="No","Not required: no personal data",IF(OR(D5="Yes",E5="Yes",F5="Yes",G5="Yes"),"Required: before processing","Not required: record the reason"))) -> Required: before processing | L5: =IF(H5="","",IF(AND(H5="Yes",I5="Yes",J5<>"",J5<>"None of these"),"Required: before first use, from 2 Dec 2027","Not required: record the reason")) -> Not required: record the reason | M5: Flags claims and holds payment pending review: a similarly significant effect. Processes health claims data at scale. Fraud detection is not an Annex III use, so no FRIA. | N5: Head of Claims
A6: S3 | B6: Customer service assistant | C6: Yes | D6: No | E6: No | F6: No | G6: No | H6: Yes | I6: No | J6: None of these | K6: =IF(C6="","",IF(C6="No","Not required: no personal data",IF(OR(D6="Yes",E6="Yes",F6="Yes",G6="Yes"),"Required: before processing","Not required: record the reason"))) -> Not required: record the reason | L6: =IF(H6="","",IF(AND(H6="Yes",I6="Yes",J6<>"",J6<>"None of these"),"Required: before first use, from 2 Dec 2027","Not required: record the reason")) -> Not required: record the reason | M6: Answers policy questions; no decisions about customers; health details are declined and routed to a person. Not high risk on the screen. AI Act transparency duty to tell users they are talking to an AI applies separately (Art 50). | N6: Head of Customer Operations
A7: S4 | B7: Marketing send-time optimiser | C7: Yes | D7: No | E7: No | F7: No | G7: No | H7: Yes | I7: No | J7: None of these | K7: =IF(C7="","",IF(C7="No","Not required: no personal data",IF(OR(D7="Yes",E7="Yes",F7="Yes",G7="Yes"),"Required: before processing","Not required: record the reason"))) -> Not required: record the reason | L7: =IF(H7="","",IF(AND(H7="Yes",I7="Yes",J7<>"",J7<>"None of these"),"Required: before first use, from 2 Dec 2027","Not required: record the reason")) -> Not required: record the reason | M7: Chooses when to send marketing emails to customers who opted in. No decisions with legal or similar effects; no special category data. | N7: Marketing Director

Sheet DPIA
A1: DPIA
A2: Data protection impact assessment for UW-1, structured on Article 35(7).
A3: Section | B3: What to record | C3: Worked example: UW-1 | D3: Source
A4: Scope | B4: System, owner, date, version | C4: UW-1 underwriting model, v2.3. Owner: Chief Underwriting Officer. Assessment dated before go-live; review on every retrain. | D4: Art 35(1)
A5: (a) Description | B5: What the processing is, step by step | C5: Applicant submits the application and declared medical history; where the answers call for it, a GP report is requested with the applicant's consent; wellness-programme members share daily step count. UW-1 returns accept, decline or a premium loading. Underwriters review every decline and every loading before the customer is told. | D5: Art 35(7)(a)
A6: (a) Purposes | B6: Why it is done | C6: Assess the insurance risk of an individual applicant and set the premium. | D6: Art 35(7)(a)
A7: (a) Data | B7: Which personal data, from where | C7: Identity and contact data; declared medical history and GP reports (health data); step count from the wearable (reclassified as health data, see finding); policy and claims history. | D7: Art 35(7)(a)
A8: (a) People | B8: Whose data, and who is affected | C8: Applicants for individual health and life cover in the UK and Ireland; dependants named on a policy. | D8: Art 35(7)(a)
A9: (b) Necessity | B9: Is each data item needed for the purpose? | C9: Declared medical history and GP reports: needed for risk assessment. Step count: not needed to assess risk; retained only to award wellness discounts. Decision: step count may lower a premium, never raise it or decline. | D9: Art 35(7)(b)
A10: (b) Proportionality | B10: Could the purpose be met with less? | C10: GP reports requested only where the application answers call for one, and limited to the conditions declared. Step count held as a monthly average, not daily detail. Raw wearable data deleted after 90 days. | D10: Art 35(7)(b)
A11: (b) Lawful basis | B11: Basis for processing, and the Article 9 condition for health data | C11: Recorded decision: separate explicit consent for the wearable feed, outside the application. Counsel to confirm the Article 9 condition relied on for application health data. | D11: Arts 6, 9
A12: (b) Automated decisions | B12: Are any significant decisions on health data solely automated? | C12: No adverse decision is: every decline and every loading is reviewed by an underwriter before the customer is told (UK GDPR Art 22B). Standard-rate accepts go out automatically; counsel to confirm they are not significant decisions for Art 22A. | D12: Arts 22A-22C
A13: (c) Risks | B13: Risks to people's rights and freedoms | C13: See the Risks sheet, rows R1-R9, rated before and after the measures. | D13: Art 35(7)(c)
A14: (d) Measures | B14: Safeguards and security | C14: See the Risks sheet, column H. Headline measures: step count upside-only; underwriter review of declines and high loadings; explanation and challenge route for every decision; fairness test by group before each release; encryption and pseudonymised training data. | D14: Art 35(7)(d)
... A19: Review | B19: What re-opens this assessment | C19: Any retrain; any new data source; a change in who the model is used on; a complaint pattern; any indicator crossing its threshold; annual review as a backstop. | D19: Art 35(11)

Sheet FRIA
A1: FRIA
A2: Fundamental rights impact assessment for UW-1 as deployed in the EU, structured on Article 27(1).
A3: Element | B3: What to record | C3: Worked example: UW-1 (EU use) | D3: Cross-reference to the DPIA (Art 27(4)) | E3: Source
A4: (a) Processes | B4: The deployer's processes the system is used in | C4: New-business underwriting for individual health and life cover sold by the Irish subsidiary. | D4: DPIA rows (a) Description, (a) Purposes | E4: Art 27(1)(a)
A5: (b) Period and frequency | B5: When, and how often, it is used | C5: Every application, continuously; about 1,200 EU applications a month. Re-run at renewal only if the customer asks for a re-quote. | D5: - | E5: Art 27(1)(b)
A6: (c) People affected | B6: Categories of people and groups likely to be affected | C6: EU applicants and named dependants; groups with a higher share of disability or chronic illness; older applicants; applicants without a wearable. | D6: DPIA row (a) People | E6: Art 27(1)(c)
A7: (d) Specific risks of harm | B7: Risks to those people, using the provider's information | C7: R2 indirect discrimination through activity data; R3 decisions without human review; R4 a GP report matched to the wrong applicant; R5 drift after retrain; R9 health information leaking through the model itself. Provider information: the model card and instructions for use (the insurer is its own provider). | D7: Risks sheet R2-R5, R9 | E7: Art 27(1)(d)
A8: (e) Human oversight | B8: How oversight is implemented, per the instructions for use | C8: Underwriter review of every decline and every loading before the customer is told; authority to overturn; weekly sample review of accepts. | D8: DPIA row (d) Measures | E8: Art 27(1)(e)
A9: (f) If risks materialise | B9: Measures, internal governance and complaints | C9: Complaint route in every decision letter; re-underwriting by a person on request; suspend the model if an indicator crosses its threshold; incident reported to the AI governance committee. | D9: Risks sheet, measures column | E9: Art 27(1)(f)
A10: Notification | B10: Results notified to the market surveillance authority | C10: Before first use after 2 December 2027, using the AI Office template once published. | D10: - | E10: Art 27(3), (5)
A11: Update | B11: When the assessment is updated | C11: Whenever any element above changes or is out of date, at minimum on every retrain. | D11: - | E11: Art 27(2)

Sheet Risks
A1: Risks
A2: One row per risk to people. Rate before (D, E) and after the measure (J, K); score and band are calculated.
A3: Risk ID | B3: Who is harmed | C3: If ... then ... (the risk as a statement) | D3: Severity to people (1-4) | E3: Likelihood (1-4) | F3: Score | G3: Band | H3: Measure | I3: Owner | J3: Residual severity (1-4) | K3: Residual likelihood (1-4) | L3: Residual score | M3: Residual band | N3: Status | O3: Assessment | P3: Risk register ID
A4: R1 | B4: Wellness-programme members | C4: If the step count is treated as lifestyle data, then health data is processed without the right condition and without the member's informed choice | D4: 3 | E4: 3 | F4: =IF(OR(D4="",E4=""),"",D4*E4) -> 9 | G4: =IF(F4="","",IF(F4>=12,"Critical",IF(F4>=8,"High",IF(F4>=4,"Medium","Low")))) -> High | H4: Reclassify as health data; separate explicit consent outside the application; purpose limited to discounts | I4: Data Protection Officer | J4: 3 | K4: 1 | L4: =IF(OR(J4="",K4=""),"",J4*K4) -> 3 | M4: =IF(L4="","",IF(L4>=12,"Critical",IF(L4>=8,"High",IF(L4>=4,"Medium","Low")))) -> Low | N4: closed | O4: DPIA | P4: RR-UW-01
A5: R2 | B5: Applicants with a disability or chronic illness | C5: If low activity raises premiums or triggers declines, then people who cannot walk much pay more or lose cover for a reason unrelated to insurable risk | D5: 4 | E5: 3 | F5: =IF(OR(D5="",E5=""),"",D5*E5) -> 12 | G5: =IF(F5="","",IF(F5>=12,"Critical",IF(F5>=8,"High",IF(F5>=4,"Medium","Low")))) -> Critical | H5: Step count upside-only: it can lower a premium, never raise it or decline; fairness test by group before each release | I5: Chief Underwriting Officer | J5: 2 | K5: 1 | L5: =IF(OR(J5="",K5=""),"",J5*K5) -> 2 | M5: =IF(L5="","",IF(L5>=12,"Critical",IF(L5>=8,"High",IF(L5>=4,"Medium","Low")))) -> Low | N5: closed | O5: Both | P5: RR-UW-02
A6: R3 | B6: All applicants | C6: If declines and loadings go out without human review, then people receive significant decisions no one checked and cannot easily contest | D6: 4 | E6: 3 | F6: =IF(OR(D6="",E6=""),"",D6*E6) -> 12 | G6: =IF(F6="","",IF(F6>=12,"Critical",IF(F6>=8,"High",IF(F6>=4,"Medium","Low")))) -> Critical | H6: Underwriter review of every decline and every loading before the customer is told, so no adverse decision on health data is solely automated (UK GDPR Art 22B); explanation and challenge route in each letter | I6: Head of Underwriting Operations | J6: 3 | K6: 1 | L6: =IF(OR(J6="",K6=""),"",J6*K6) -> 3 | M6: =IF(L6="","",IF(L6>=12,"Critical",IF(L6>=8,"High",IF(L6>=4,"Medium","Low")))) -> Low | N6: mitigating | O6: Both | P6: RR-UW-03
A7: R4 | B7: Applicants whose GP report is requested | C7: If a GP report is matched to the wrong applicant, then the model loads or declines on someone else's medical history | D7: 3 | E7: 2 | F7: =IF(OR(D7="",E7=""),"",D7*E7) -> 6 | G7: =IF(F7="","",IF(F7>=12,"Critical",IF(F7>=8,"High",IF(F7>=4,"Medium","Low")))) -> Medium | H7: Identity check on every GP report received; the applicant is told what evidence was used and can correct it before a decision | I7: Head of Data | J7: 3 | K7: 1 | L7: =IF(OR(J7="",K7=""),"",J7*K7) -> 3 | M7: =IF(L7="","",IF(L7>=12,"Critical",IF(L7>=8,"High",IF(L7>=4,"Medium","Low")))) -> Low | N7: mitigating | O7: Both | P7: RR-UW-04
A8: R5 | B8: All applicants | C8: If a retrain shifts prices for one group, then the change reaches customers unnoticed | D8: 3 | E8: 2 | F8: =IF(OR(D8="",E8=""),"",D8*E8) -> 6 | G8: =IF(F8="","",IF(F8>=12,"Critical",IF(F8>=8,"High",IF(F8>=4,"Medium","Low")))) -> Medium | H8: Group-level price monitoring; retrain re-opens both assessments | I8: Model Risk Manager | J8: 3 | K8: 1 | L8: =IF(OR(J8="",K8=""),"",J8*K8) -> 3 | M8: =IF(L8="","",IF(L8>=12,"Critical",IF(L8>=8,"High",IF(L8>=4,"Medium","Low")))) -> Low | N8: open | O8: Both | P8: RR-UW-05
A9: R6 | B9: All applicants | C9: If applicants are not told AI is used or how to challenge, then they cannot exercise their rights | D9: 2 | E9: 3 | F9: =IF(OR(D9="",E9=""),"",D9*E9) -> 6 | G9: =IF(F9="","",IF(F9>=12,"Critical",IF(F9>=8,"High",IF(F9>=4,"Medium","Low")))) -> Medium | H9: Notice at application; explanation on request; route to a person | I9: Head of Customer Operations | J9: 2 | K9: 1 | L9: =IF(OR(J9="",K9=""),"",J9*K9) -> 2 | M9: =IF(L9="","",IF(L9>=12,"Critical",IF(L9>=8,"High",IF(L9>=4,"Medium","Low")))) -> Low | N9: closed | O9: DPIA | P9: RR-UW-06
A10: R7 | B10: Wellness-programme members | C10: If raw wearable data is kept indefinitely, then far more health detail is held than the purpose needs | D10: 2 | E10: 3 | F10: =IF(OR(D10="",E10=""),"",D10*E10) -> 6 | G10: =IF(F10="","",IF(F10>=12,"Critical",IF(F10>=8,"High",IF(F10>=4,"Medium","Low")))) -> Medium | H10: Monthly average only; raw data deleted after 90 days | I10: Data Protection Officer | J10: 2 | K10: 1 | L10: =IF(OR(J10="",K10=""),"",J10*K10) -> 2 | M10: =IF(L10="","",IF(L10>=12,"Critical",IF(L10>=8,"High",IF(L10>=4,"Medium","Low")))) -> Low | N10: closed | O10: DPIA | P10: RR-UW-07
A11: R8 | B11: All applicants | C11: If the underwriting data store is breached, then medical histories are exposed | D11: 4 | E11: 2 | F11: =IF(OR(D11="",E11=""),"",D11*E11) -> 8 | G11: =IF(F11="","",IF(F11>=12,"Critical",IF(F11>=8,"High",IF(F11>=4,"Medium","Low")))) -> High | H11: Encryption at rest and in transit; role-based access; pseudonymised training data | I11: Chief Information Security Officer | J11: 4 | K11: 1 | L11: =IF(OR(J11="",K11=""),"",J11*K11) -> 4 | M11: =IF(L11="","",IF(L11>=12,"Critical",IF(L11>=8,"High",IF(L11>=4,"Medium","Low")))) -> Medium | N11: mitigating | O11: DPIA | P11: RR-UW-08
A12: R9 | B12: Applicants and customers whose records trained the model | C12: If the model can be queried in a way that reveals whether a person's records were in its training data (a membership-inference attack), then that person's health information leaks without any system being breached | D12: 3 | E12: 2 | F12: =IF(OR(D12="",E12=""),"",D12*E12) -> 6 | G12: =IF(F12="","",IF(F12>=12,"Critical",IF(F12>=8,"High",IF(F12>=4,"Medium","Low")))) -> Medium | H12: Model not exposed outside the underwriting platform; only the decision is returned, never scores or confidence values; query rate limits; membership-inference test before each release | I12: Head of Data Science | J12: 3 | K12: 1 | L12: =IF(OR(J12="",K12=""),"",J12*K12) -> 3 | M12: =IF(L12="","",IF(L12>=12,"Critical",IF(L12>=8,"High",IF(L12>=4,"Medium","Low")))) -> Low | N12: open | O12: Both | P12: RR-UW-09

Sheet Screening Template
A1: Screening Template
A2: One row per AI system. Answer C-J; K and L are calculated. Where an assessment is not required, record the reason in M.
A3: ID | B3: AI system | C3: Processes personal data? | D3: Automated evaluation or profiling with legal or similarly significant effects? (Art 35(3)(a)) | E3: Special category data (e.g. health) at large scale? (Art 35(3)(b)) | F3: Systematic monitoring of a public area at large scale? (Art 35(3)(c)) | G3: Otherwise likely to be high risk to people? (Art 35(1)) | H3: Used in the EU? | I3: High-risk under Annex III (other than point 2)? | J3: Deployer type (Art 27(1)) | K3: DPIA | L3: FRIA | M3: Reason recorded / notes | N3: Decision owner
K4: =IF(C4="","",IF(C4="No","Not required: no personal data",IF(OR(D4="Yes",E4="Yes",F4="Yes",G4="Yes"),"Required: before processing","Not required: record the reason"))) | L4: =IF(H4="","",IF(AND(H4="Yes",I4="Yes",J4<>"",J4<>"None of these"),"Required: before first use, from 2 Dec 2027","Not required: record the reason"))
K5: =IF(C5="","",IF(C5="No","Not required: no personal data",IF(OR(D5="Yes",E5="Yes",F5="Yes",G5="Yes"),"Required: before processing","Not required: record the reason"))) | L5: =IF(H5="","",IF(AND(H5="Yes",I5="Yes",J5<>"",J5<>"None of these"),"Required: before first use, from 2 Dec 2027","Not required: record the reason"))
K6: =IF(C6="","",IF(C6="No","Not required: no personal data",IF(OR(D6="Yes",E6="Yes",F6="Yes",G6="Yes"),"Required: before processing","Not required: record the reason"))) | L6: =IF(H6="","",IF(AND(H6="Yes",I6="Yes",J6<>"",J6<>"None of these"),"Required: before first use, from 2 Dec 2027","Not required: record the reason"))
K7: =IF(C7="","",IF(C7="No","Not required: no personal data",IF(OR(D7="Yes",E7="Yes",F7="Yes",G7="Yes"),"Required: before processing","Not required: record the reason"))) | L7: =IF(H7="","",IF(AND(H7="Yes",I7="Yes",J7<>"",J7<>"None of these"),"Required: before first use, from 2 Dec 2027","Not required: record the reason"))
K8: =IF(C8="","",IF(C8="No","Not required: no personal data",IF(OR(D8="Yes",E8="Yes",F8="Yes",G8="Yes"),"Required: before processing","Not required: record the reason"))) | L8: =IF(H8="","",IF(AND(H8="Yes",I8="Yes",J8<>"",J8<>"None of these"),"Required: before first use, from 2 Dec 2027","Not required: record the reason"))
K9: =IF(C9="","",IF(C9="No","Not required: no personal data",IF(OR(D9="Yes",E9="Yes",F9="Yes",G9="Yes"),"Required: before processing","Not required: record the reason"))) | L9: =IF(H9="","",IF(AND(H9="Yes",I9="Yes",J9<>"",J9<>"None of these"),"Required: before first use, from 2 Dec 2027","Not required: record the reason"))
K10: =IF(C10="","",IF(C10="No","Not required: no personal data",IF(OR(D10="Yes",E10="Yes",F10="Yes",G10="Yes"),"Required: before processing","Not required: record the reason"))) | L10: =IF(H10="","",IF(AND(H10="Yes",I10="Yes",J10<>"",J10<>"None of these"),"Required: before first use, from 2 Dec 2027","Not required: record the reason"))
K11: =IF(C11="","",IF(C11="No","Not required: no personal data",IF(OR(D11="Yes",E11="Yes",F11="Yes",G11="Yes"),"Required: before processing","Not required: record the reason"))) | L11: =IF(H11="","",IF(AND(H11="Yes",I11="Yes",J11<>"",J11<>"None of these"),"Required: before first use, from 2 Dec 2027","Not required: record the reason"))
K12: =IF(C12="","",IF(C12="No","Not required: no personal data",IF(OR(D12="Yes",E12="Yes",F12="Yes",G12="Yes"),"Required: before processing","Not required: record the reason"))) | L12: =IF(H12="","",IF(AND(H12="Yes",I12="Yes",J12<>"",J12<>"None of these"),"Required: before first use, from 2 Dec 2027","Not required: record the reason"))
K13: =IF(C13="","",IF(C13="No","Not required: no personal data",IF(OR(D13="Yes",E13="Yes",F13="Yes",G13="Yes"),"Required: before processing","Not required: record the reason"))) | L13: =IF(H13="","",IF(AND(H13="Yes",I13="Yes",J13<>"",J13<>"None of these"),"Required: before first use, from 2 Dec 2027","Not required: record the reason"))
K14: =IF(C14="","",IF(C14="No","Not required: no personal data",IF(OR(D14="Yes",E14="Yes",F14="Yes",G14="Yes"),"Required: before processing","Not required: record the reason"))) | L14: =IF(H14="","",IF(AND(H14="Yes",I14="Yes",J14<>"",J14<>"None of these"),"Required: before first use, from 2 Dec 2027","Not required: record the reason"))
K15: =IF(C15="","",IF(C15="No","Not required: no personal data",IF(OR(D15="Yes",E15="Yes",F15="Yes",G15="Yes"),"Required: before processing","Not required: record the reason"))) | L15: =IF(H15="","",IF(AND(H15="Yes",I15="Yes",J15<>"",J15<>"None of these"),"Required: before first use, from 2 Dec 2027","Not required: record the reason"))
... K28: =IF(C28="","",IF(C28="No","Not required: no personal data",IF(OR(D28="Yes",E28="Yes",F28="Yes",G28="Yes"),"Required: before processing","Not required: record the reason"))) | L28: =IF(H28="","",IF(AND(H28="Yes",I28="Yes",J28<>"",J28<>"None of these"),"Required: before first use, from 2 Dec 2027","Not required: record the reason"))

Sheet DPIA Template
A1: DPIA Template
A2: Blank DPIA. Fill the yellow cells. Delete the Finding row if it does not apply.
A3: Section | B3: What to record | C3: Your answer | D3: Source
A4: Scope | B4: System, owner, date, version | D4: Art 35(1)
A5: (a) Description | B5: What the processing is, step by step | D5: Art 35(7)(a)
A6: (a) Purposes | B6: Why it is done | D6: Art 35(7)(a)
A7: (a) Data | B7: Which personal data, from where | D7: Art 35(7)(a)
A8: (a) People | B8: Whose data, and who is affected | D8: Art 35(7)(a)
A9: (b) Necessity | B9: Is each data item needed for the purpose? | D9: Art 35(7)(b)
A10: (b) Proportionality | B10: Could the purpose be met with less? | D10: Art 35(7)(b)
A11: (b) Lawful basis | B11: Basis for processing, and the Article 9 condition for health data | D11: Arts 6, 9
A12: (b) Automated decisions | B12: Are any significant decisions on health data solely automated? | D12: Arts 22A-22C
A13: (c) Risks | B13: Risks to people's rights and freedoms | D13: Art 35(7)(c)
A14: (d) Measures | B14: Safeguards and security | D14: Art 35(7)(d)
A15: Finding | B15: What the assessment changed | D15: Art 4(15)
... A19: Review | B19: What re-opens this assessment | D19: Art 35(11)

Sheet FRIA Template
A1: FRIA Template
A2: Blank FRIA. Fill the yellow cells; point to the DPIA wherever it already covers an element.
A3: Element | B3: What to record | C3: Your answer | D3: Cross-reference to the DPIA (Art 27(4)) | E3: Source
A4: (a) Processes | B4: The deployer's processes the system is used in | E4: Art 27(1)(a)
A5: (b) Period and frequency | B5: When, and how often, it is used | E5: Art 27(1)(b)
A6: (c) People affected | B6: Categories of people and groups likely to be affected | E6: Art 27(1)(c)
A7: (d) Specific risks of harm | B7: Risks to those people, using the provider's information | E7: Art 27(1)(d)
A8: (e) Human oversight | B8: How oversight is implemented, per the instructions for use | E8: Art 27(1)(e)
A9: (f) If risks materialise | B9: Measures, internal governance and complaints | E9: Art 27(1)(f)
A10: Notification | B10: Results notified to the market surveillance authority | E10: Art 27(3), (5)
A11: Update | B11: When the assessment is updated | E11: Art 27(2)

Sheet Risks Template
A1: Risks Template
A2: One row per risk to people. Rate before (D, E) and after the measure (J, K); score and band are calculated.
A3: Risk ID | B3: Who is harmed | C3: If ... then ... (the risk as a statement) | D3: Severity to people (1-4) | E3: Likelihood (1-4) | F3: Score | G3: Band | H3: Measure | I3: Owner | J3: Residual severity (1-4) | K3: Residual likelihood (1-4) | L3: Residual score | M3: Residual band | N3: Status | O3: Assessment | P3: Risk register ID
F4: =IF(OR(D4="",E4=""),"",D4*E4) | G4: =IF(F4="","",IF(F4>=12,"Critical",IF(F4>=8,"High",IF(F4>=4,"Medium","Low")))) | L4: =IF(OR(J4="",K4=""),"",J4*K4) | M4: =IF(L4="","",IF(L4>=12,"Critical",IF(L4>=8,"High",IF(L4>=4,"Medium","Low"))))
F5: =IF(OR(D5="",E5=""),"",D5*E5) | G5: =IF(F5="","",IF(F5>=12,"Critical",IF(F5>=8,"High",IF(F5>=4,"Medium","Low")))) | L5: =IF(OR(J5="",K5=""),"",J5*K5) | M5: =IF(L5="","",IF(L5>=12,"Critical",IF(L5>=8,"High",IF(L5>=4,"Medium","Low"))))
F6: =IF(OR(D6="",E6=""),"",D6*E6) | G6: =IF(F6="","",IF(F6>=12,"Critical",IF(F6>=8,"High",IF(F6>=4,"Medium","Low")))) | L6: =IF(OR(J6="",K6=""),"",J6*K6) | M6: =IF(L6="","",IF(L6>=12,"Critical",IF(L6>=8,"High",IF(L6>=4,"Medium","Low"))))
F7: =IF(OR(D7="",E7=""),"",D7*E7) | G7: =IF(F7="","",IF(F7>=12,"Critical",IF(F7>=8,"High",IF(F7>=4,"Medium","Low")))) | L7: =IF(OR(J7="",K7=""),"",J7*K7) | M7: =IF(L7="","",IF(L7>=12,"Critical",IF(L7>=8,"High",IF(L7>=4,"Medium","Low"))))
F8: =IF(OR(D8="",E8=""),"",D8*E8) | G8: =IF(F8="","",IF(F8>=12,"Critical",IF(F8>=8,"High",IF(F8>=4,"Medium","Low")))) | L8: =IF(OR(J8="",K8=""),"",J8*K8) | M8: =IF(L8="","",IF(L8>=12,"Critical",IF(L8>=8,"High",IF(L8>=4,"Medium","Low"))))
F9: =IF(OR(D9="",E9=""),"",D9*E9) | G9: =IF(F9="","",IF(F9>=12,"Critical",IF(F9>=8,"High",IF(F9>=4,"Medium","Low")))) | L9: =IF(OR(J9="",K9=""),"",J9*K9) | M9: =IF(L9="","",IF(L9>=12,"Critical",IF(L9>=8,"High",IF(L9>=4,"Medium","Low"))))
F10: =IF(OR(D10="",E10=""),"",D10*E10) | G10: =IF(F10="","",IF(F10>=12,"Critical",IF(F10>=8,"High",IF(F10>=4,"Medium","Low")))) | L10: =IF(OR(J10="",K10=""),"",J10*K10) | M10: =IF(L10="","",IF(L10>=12,"Critical",IF(L10>=8,"High",IF(L10>=4,"Medium","Low"))))
F11: =IF(OR(D11="",E11=""),"",D11*E11) | G11: =IF(F11="","",IF(F11>=12,"Critical",IF(F11>=8,"High",IF(F11>=4,"Medium","Low")))) | L11: =IF(OR(J11="",K11=""),"",J11*K11) | M11: =IF(L11="","",IF(L11>=12,"Critical",IF(L11>=8,"High",IF(L11>=4,"Medium","Low"))))
F12: =IF(OR(D12="",E12=""),"",D12*E12) | G12: =IF(F12="","",IF(F12>=12,"Critical",IF(F12>=8,"High",IF(F12>=4,"Medium","Low")))) | L12: =IF(OR(J12="",K12=""),"",J12*K12) | M12: =IF(L12="","",IF(L12>=12,"Critical",IF(L12>=8,"High",IF(L12>=4,"Medium","Low"))))
F13: =IF(OR(D13="",E13=""),"",D13*E13) | G13: =IF(F13="","",IF(F13>=12,"Critical",IF(F13>=8,"High",IF(F13>=4,"Medium","Low")))) | L13: =IF(OR(J13="",K13=""),"",J13*K13) | M13: =IF(L13="","",IF(L13>=12,"Critical",IF(L13>=8,"High",IF(L13>=4,"Medium","Low"))))
F14: =IF(OR(D14="",E14=""),"",D14*E14) | G14: =IF(F14="","",IF(F14>=12,"Critical",IF(F14>=8,"High",IF(F14>=4,"Medium","Low")))) | L14: =IF(OR(J14="",K14=""),"",J14*K14) | M14: =IF(L14="","",IF(L14>=12,"Critical",IF(L14>=8,"High",IF(L14>=4,"Medium","Low"))))
F15: =IF(OR(D15="",E15=""),"",D15*E15) | G15: =IF(F15="","",IF(F15>=12,"Critical",IF(F15>=8,"High",IF(F15>=4,"Medium","Low")))) | L15: =IF(OR(J15="",K15=""),"",J15*K15) | M15: =IF(L15="","",IF(L15>=12,"Critical",IF(L15>=8,"High",IF(L15>=4,"Medium","Low"))))
... F28: =IF(OR(D28="",E28=""),"",D28*E28) | G28: =IF(F28="","",IF(F28>=12,"Critical",IF(F28>=8,"High",IF(F28>=4,"Medium","Low")))) | L28: =IF(OR(J28="",K28=""),"",J28*K28) | M28: =IF(L28="","",IF(L28>=12,"Critical",IF(L28>=8,"High",IF(L28>=4,"Medium","Low"))))
